ghasedak/__init__.py
ghasedak/ghasedak.py
ghasedak-0.1.7.dist-info/DESCRIPTION.rst
ghasedak-0.1.7.dist-info/METADATA
ghasedak-0.1.7.dist-info/RECORD
ghasedak-0.1.7.dist-info/WHEEL
ghasedak-0.1.7.dist-info/metadata.json
ghasedak-0.1.7.dist-info/top_level.txt
